pytool_proxy_fix/__init__.py
pytool_proxy_fix/fix_urllib_https.py
pytool_proxy_fix/main.py
pytool_proxy_fix-0.1.2.dist-info/LICENSE
pytool_proxy_fix-0.1.2.dist-info/METADATA
pytool_proxy_fix-0.1.2.dist-info/WHEEL
pytool_proxy_fix-0.1.2.dist-info/entry_points.txt
pytool_proxy_fix-0.1.2.dist-info/top_level.txt
pytool_proxy_fix-0.1.2.dist-info/RECORD
