Metadata-Version: 2.1
Name: pytool-proxy-fix
Version: 0.1.2
Summary: Fix urllib for python 3.7/3.8
Home-page: https://github.com/kites262/tool-fix-urllib
Author: kites262
Author-email: kites262@github.com
License: MIT
Classifier: Programming Language :: Python :: 3.7
Classifier: Programming Language :: Python :: 3.8
Classifier: License :: OSI Approved :: MIT License
Classifier: Operating System :: OS Independent
Requires-Python: >=3.7, <3.9
License-File: LICENSE
